README.rst
setup.cfg
setup.py
examples/__init__.py
examples/custom_app.py
examples/chat/__init__.py
examples/chat/custom.py
sethpusher/__init__.py
sethpusher/applications.py
sethpusher/authenticators.py
sethpusher/default_server.py
sethpusher/dispatchers.py
sethpusher/mixins.py
sethpusher/persistors.py
sethpusher/utils.py
sethpusher.egg-info/PKG-INFO
sethpusher.egg-info/SOURCES.txt
sethpusher.egg-info/dependency_links.txt
sethpusher.egg-info/entry_points.txt
sethpusher.egg-info/not-zip-safe
sethpusher.egg-info/requires.txt
sethpusher.egg-info/top_level.txt
sethpusher/api/__init__.py
sethpusher/api/urls.py
sethpusher/api/views.py
sethpusher/ws/__init__.py
sethpusher/ws/urls.py
sethpusher/ws/views.py