Metadata-Version: 1.1
Name: sethpusher
Version: 0.2.2
Summary: Tornado based pub/sub server powered by sockjs. Designed as a set of components.
Home-page: https://github.com/jnosal/seth-pusher
Author: jnosal
Author-email: jacek.nosal@outlook.com
License: UNKNOWN
Keywords: seth,tornado,push-server
Platform: UNKNOWN
Classifier: Development Status :: 1 - Planning
Classifier: Intended Audience :: Developers
Classifier: Natural Language :: English
Classifier: License :: OSI Approved :: MIT License
Classifier: Operating System :: OS Independent
Classifier: Programming Language :: Python
Classifier: Programming Language :: Python :: 2
Classifier: Programming Language :: Python :: 2.6
Classifier: Programming Language :: Python :: 2.7
Classifier: Topic :: Software Development :: Libraries :: Python Modules
